Metadata-Version: 2.0
Name: odoo8-addon-sale-commission
Version: 8.0.3.1.1
Summary: Sales commissions
Home-page: UNKNOWN
Author: Pexego, Savoire-faire linux, Avanzosc, Abstract, Tecnativa, Odoo Community Association (OCA)
Author-email: support@odoo-community.org
License: AGPL-3
Platform: UNKNOWN
Classifier: Programming Language :: Python
Classifier: Framework :: Odoo
Classifier: License :: OSI Approved :: GNU Affero General Public License v3
Requires-Python: ~=2.7
Requires-Dist: odoo (<9.0a,>=8.0a)
Requires-Dist: odoo8-addon-web-widget-one2many-tags
